{
  "videos": [
    {
      "title": "Hi",
      "description": "This should be working now",
      "id": 1
    },
    {
      "title": "Another Stream",
      "description": "WoW now its working! Awesome",
      "id": 2
    },
    {
      "title": "Programmatic Navigation ",
      "description": "I should not be able to see that after i submit this stream",
      "userId": "116153246862163023852",
      "id": 4
    },
    {
      "title": "Programmatic Navigation Testing ",
      "description": "I wish you the best of luck Done!!",
      "userId": "116153246862163023852",
      "id": 5
    },
    {
      "title": "Put VS Patch",
      "description": "sometimes small differences lead to bigger differences ",
      "userId": "116153246862163023852",
      "id": 6
    },
    {
      "title": "Testing",
      "description": "Code reusability testing. Lets see how it works",
      "id": 7
    }
  ]
}